odoo/addons/web_view_calendar_list/README.rst
odoo/addons/web_view_calendar_list/__init__.py
odoo/addons/web_view_calendar_list/__manifest__.py
odoo/addons/web_view_calendar_list/i18n/ca.po
odoo/addons/web_view_calendar_list/i18n/es.po
odoo/addons/web_view_calendar_list/i18n/it.po
odoo/addons/web_view_calendar_list/i18n/pt_BR.po
odoo/addons/web_view_calendar_list/i18n/web_view_calendar_list.pot
odoo/addons/web_view_calendar_list/models/__init__.py
odoo/addons/web_view_calendar_list/models/ir_actions_act_window_view.py
odoo/addons/web_view_calendar_list/models/ir_ui_view.py
odoo/addons/web_view_calendar_list/readme/CONTRIBUTORS.rst
odoo/addons/web_view_calendar_list/readme/DESCRIPTION.rst
odoo/addons/web_view_calendar_list/readme/USAGE.rst
odoo/addons/web_view_calendar_list/static/description/icon.png
odoo/addons/web_view_calendar_list/static/description/index.html
odoo/addons/web_view_calendar_list/static/src/js/calendar_list_controller.js
odoo/addons/web_view_calendar_list/static/src/js/calendar_list_model.js
odoo/addons/web_view_calendar_list/static/src/js/calendar_list_renderer.js
odoo/addons/web_view_calendar_list/static/src/js/calendar_list_view.js
odoo/addons/web_view_calendar_list/static/src/scss/web_calendar_list.scss
odoo/addons/web_view_calendar_list/templates/assets.xml
odoo14_addon_web_view_calendar_list-14.0.1.0.1.dev9.dist-info/METADATA
odoo14_addon_web_view_calendar_list-14.0.1.0.1.dev9.dist-info/WHEEL
odoo14_addon_web_view_calendar_list-14.0.1.0.1.dev9.dist-info/top_level.txt
odoo14_addon_web_view_calendar_list-14.0.1.0.1.dev9.dist-info/RECORD
